config_tempest/__init__.py
config_tempest/accounts.py
config_tempest/clients.py
config_tempest/constants.py
config_tempest/credentials.py
config_tempest/flavors.py
config_tempest/main.py
config_tempest/profile.py
config_tempest/tempest_conf.py
config_tempest/users.py
config_tempest/utils.py
config_tempest/services/__init__.py
config_tempest/services/alarming.py
config_tempest/services/aws.py
config_tempest/services/baremetal.py
config_tempest/services/base.py
config_tempest/services/ceilometer.py
config_tempest/services/compute.py
config_tempest/services/data-processing.py
config_tempest/services/database.py
config_tempest/services/dns.py
config_tempest/services/event.py
config_tempest/services/horizon.py
config_tempest/services/identity.py
config_tempest/services/image.py
config_tempest/services/key_manager.py
config_tempest/services/messaging.py
config_tempest/services/metric.py
config_tempest/services/network.py
config_tempest/services/object_storage.py
config_tempest/services/octavia.py
config_tempest/services/orchestration.py
config_tempest/services/placement.py
config_tempest/services/services.py
config_tempest/services/share.py
config_tempest/services/telemetry.py
config_tempest/services/volume.py
config_tempest/services/watcher.py
config_tempest/services/workflowv2.py
config_tempest/tests/__init__.py
config_tempest/tests/base.py
config_tempest/tests/test_accounts.py
config_tempest/tests/test_clients.py
config_tempest/tests/test_config_tempest.py
config_tempest/tests/test_credentials.py
config_tempest/tests/test_flavors.py
config_tempest/tests/test_profile.py
config_tempest/tests/test_tempest_conf.py
config_tempest/tests/test_users.py
config_tempest/tests/test_utils.py
config_tempest/tests/services/__init__.py
config_tempest/tests/services/test_aws.py
config_tempest/tests/services/test_base.py
config_tempest/tests/services/test_ceilometer.py
config_tempest/tests/services/test_compute.py
config_tempest/tests/services/test_horizon.py
python_tempestconf-3.5.2.dist-info/AUTHORS
python_tempestconf-3.5.2.dist-info/LICENSE
python_tempestconf-3.5.2.dist-info/METADATA
python_tempestconf-3.5.2.dist-info/WHEEL
python_tempestconf-3.5.2.dist-info/entry_points.txt
python_tempestconf-3.5.2.dist-info/pbr.json
python_tempestconf-3.5.2.dist-info/top_level.txt
python_tempestconf-3.5.2.dist-info/RECORD
