Metadata-Version: 2.1
Name: python-tempestconf
Version: 3.5.2
Summary: python-tempestconf will automatically generates the tempest configuration based on your cloud.
Home-page: https://pypi.org/project/python-tempestconf
Author: OpenStack
Author-email: openstack-discuss@lists.openstack.org
Classifier: Environment :: OpenStack
Classifier: Intended Audience :: Information Technology
Classifier: Intended Audience :: System Administrators
Classifier: License :: OSI Approved :: Apache Software License
Classifier: Operating System :: POSIX :: Linux
Classifier: Programming Language :: Python
Classifier: Programming Language :: Python :: Implementation :: CPython
Classifier: Programming Language :: Python :: 3 :: Only
Classifier: Programming Language :: Python :: 3
Classifier: Programming Language :: Python :: 3.8
Classifier: Programming Language :: Python :: 3.9
Classifier: Programming Language :: Python :: 3.10
Classifier: Programming Language :: Python :: 3.11
Classifier: Programming Language :: Python :: 3.12
Requires-Python: >=3.8
License-File: LICENSE
License-File: AUTHORS
Requires-Dist: pbr >=1.8
Requires-Dist: six >=1.10.0
Requires-Dist: tempest >=14.0.0
Requires-Dist: requests !=2.12.2,>=2.10.0
Requires-Dist: openstacksdk >=0.11.3
Requires-Dist: oslo.config >=3.23.0
Requires-Dist: tenacity >=5.1.1
Requires-Dist: PyYAML >=3.12
